tekwfm2/__init__.py
tekwfm2/tekwfm.py
tekwfm2-0.1.1.dist-info/LICENSE
tekwfm2-0.1.1.dist-info/METADATA
tekwfm2-0.1.1.dist-info/WHEEL
tekwfm2-0.1.1.dist-info/top_level.txt
tekwfm2-0.1.1.dist-info/RECORD
